kentik_api/__init__.py
kentik_api/kentik_api.py
kentik_api/version.py
kentik_api/analytics/__init__.py
kentik_api/analytics/data_frame_cache.py
kentik_api/analytics/flatness.py
kentik_api/analytics/mapped_query.py
kentik_api/api_calls/__init__.py
kentik_api/api_calls/active_alerts.py
kentik_api/api_calls/alerts.py
kentik_api/api_calls/api_call.py
kentik_api/api_calls/api_call_decorators.py
kentik_api/api_calls/batch.py
kentik_api/api_calls/custom_applications.py
kentik_api/api_calls/custom_dimensions.py
kentik_api/api_calls/device_labels.py
kentik_api/api_calls/devices.py
kentik_api/api_calls/my_kentik_portal.py
kentik_api/api_calls/plans.py
kentik_api/api_calls/query_methods.py
kentik_api/api_calls/saved_filters.py
kentik_api/api_calls/sites.py
kentik_api/api_calls/tags.py
kentik_api/api_calls/users.py
kentik_api/api_connection/__init__.py
kentik_api/api_connection/api_call_response.py
kentik_api/api_connection/api_connector.py
kentik_api/api_connection/api_connector_protocol.py
kentik_api/api_connection/retryable_session.py
kentik_api/api_resources/__init__.py
kentik_api/api_resources/alerting_api.py
kentik_api/api_resources/base_api.py
kentik_api/api_resources/batch_api.py
kentik_api/api_resources/custom_applications_api.py
kentik_api/api_resources/custom_dimensions_api.py
kentik_api/api_resources/device_labels_api.py
kentik_api/api_resources/devices_api.py
kentik_api/api_resources/plans_api.py
kentik_api/api_resources/query_api.py
kentik_api/api_resources/saved_filters_api.py
kentik_api/api_resources/sites_api.py
kentik_api/api_resources/tags_api.py
kentik_api/api_resources/tenants_api.py
kentik_api/api_resources/users_api.py
kentik_api/auth/__init__.py
kentik_api/auth/auth.py
kentik_api/cloudexport/__init__.py
kentik_api/cloudexport/api_connector.py
kentik_api/cloudexport/api_connector_protocol.py
kentik_api/cloudexport/client.py
kentik_api/cloudexport/cloud_export.py
kentik_api/generated/kentik/cloud_export/v202101beta1/cloud_export_pb2.py
kentik_api-1.0.7.dist-info/LICENSE
kentik_api-1.0.7.dist-info/METADATA
kentik_api-1.0.7.dist-info/WHEEL
kentik_api-1.0.7.dist-info/top_level.txt
kentik_api-1.0.7.dist-info/RECORD
