Metadata-Version: 2.1
Name: kentik-api
Version: 1.0.7
Summary: Kentik API SDK
Author-email: Martin Machacek <martin.machacek@kentik.com>
Classifier: License :: OSI Approved :: Apache Software License
Classifier: Natural Language :: English
Classifier: Operating System :: OS Independent
Classifier: Programming Language :: Python
Classifier: Programming Language :: Python :: 3.8
Classifier: Programming Language :: Python :: 3.9
Classifier: Programming Language :: Python :: 3.10
Requires-Python: <4,>=3.8
License-File: LICENSE
Requires-Dist: dacite (==1.6.0)
Requires-Dist: requests[socks] (>=2.28.1)
Requires-Dist: typing-extensions (==4.3.0)
Requires-Dist: urllib3 (==1.26.12)
Requires-Dist: protobuf (==4.22.0)
Requires-Dist: grpcio (==1.51.3)
Requires-Dist: googleapis-common-protos (==1.58.0)
Requires-Dist: protoc-gen-openapiv2 (==0.0.1)
Provides-Extra: analytics
Requires-Dist: pandas (>=1.5.0) ; extra == 'analytics'
Requires-Dist: pyyaml (>=6.0) ; extra == 'analytics'
Requires-Dist: fastparquet (>=0.8.3) ; extra == 'analytics'
Provides-Extra: dev
Requires-Dist: black (==22.8.0) ; extra == 'dev'
Requires-Dist: isort (==5.10.1) ; extra == 'dev'
Requires-Dist: flake8 (==5.0.4) ; extra == 'dev'
Requires-Dist: GitPython (==3.1.27) ; extra == 'dev'
Requires-Dist: grpcio-tools (==1.51.3) ; extra == 'dev'
Requires-Dist: mypy (==0.971) ; extra == 'dev'
Requires-Dist: mypy-extensions (==0.4.3) ; extra == 'dev'
Requires-Dist: pylint (==2.15.3) ; extra == 'dev'
Requires-Dist: types-protobuf (==4.22.0) ; extra == 'dev'
Requires-Dist: types-PyYAML (==6.0.0) ; extra == 'dev'
Requires-Dist: types-requests (==2.28.1) ; extra == 'dev'
Provides-Extra: test
Requires-Dist: httpretty (==1.1.4) ; extra == 'test'
Requires-Dist: pytest (==7.1.3) ; extra == 'test'
